{"name":"build-javascript","namedChunkGroups":{"app":{"name":"app","assets":[{"name":"webpack-runtime-70d309402a64dceab578.js","size":4773},{"name":"framework-608844ff67614be9dc5b.js","size":140720},{"name":"app-5b501379a6867f1484c2.js","size":97272}],"filteredAssets":0,"assetsSize":242765,"filteredAuxiliaryAssets":3,"auxiliaryAssetsSize":618159},"component---src-pages-404-js":{"name":"component---src-pages-404-js","assets":[{"name":"component---src-pages-404-js-42d70bfc64a0e4a157dc.js","size":372}],"filteredAssets":0,"assetsSize":372,"filteredAuxiliaryAssets":1,"auxiliaryAssetsSize":475},"component---src-pages-index-js":{"name":"component---src-pages-index-js","assets":[{"name":"styles.be8ccdbc8191e7e99baf.css","size":30561},{"name":"component---src-pages-index-js-f4411dcfe1972173708b.js","size":42633}],"filteredAssets":0,"assetsSize":73194,"filteredAuxiliaryAssets":1,"auxiliaryAssetsSize":84140}},"assetsByChunkName":{"app":["webpack-runtime-70d309402a64dceab578.js","framework-608844ff67614be9dc5b.js","app-5b501379a6867f1484c2.js"],"component---src-pages-404-js":["component---src-pages-404-js-42d70bfc64a0e4a157dc.js"],"component---src-pages-index-js":["styles.be8ccdbc8191e7e99baf.css","component---src-pages-index-js-f4411dcfe1972173708b.js"]},"childAssetsByChunkName":{}}